envcleaner/__init__.py
envcleaner/__main__.py
envcleaner/cleaners/__init__.py
envcleaner/cleaners/base.py
envcleaner/cleaners/venv.py
envcleaner/main.py
envcleaner/utils.py
envcleaner-0.2.0.dist-info/METADATA
envcleaner-0.2.0.dist-info/WHEEL
envcleaner-0.2.0.dist-info/entry_points.txt
envcleaner-0.2.0.dist-info/RECORD
